Workbook

Sheet Read Me
A1: AURA Full Financial Model
A2: Что это | B2: Редактируемая модель, чтобы понять порядок инвестиций, выручки, расходов, runway и сценариев роста AURA.
A3: Валюта модели | B3: EUR. Подписка задана в USD и переводится через FX в Inputs.
A4: Главное ограничение | B4: Это hypothesis model, а не прогноз продаж. После прототипа нужно заменить assumptions фактическими данными.
A5: Как пользоваться | B5: Менять желтые/зеленые вводные на вкладке Inputs и смотреть Monthly Model, Quarterly Summary, Annual Scenarios.
A6: Что считается | B6: MAU, платящие, выручка, COGS AI/генераций, маркетинг, команда, burn, cumulative cash need, ARR run-rate.
A7: Ключевой вывод | B7: Phase 1 = €4k-€10k. Полный первый год лучше планировать как €80k-€150k runway до доказанного break-even.

Sheet Dashboard
A1: AURA Financial Dashboard
A2: Metric | B2: Value | C2: Source
A3: Peak cash need | B3: ='Monthly Model'!S37 | C3: Monthly Model
A4: Year 1 revenue | B4: ='Quarterly Summary'!D5 | C4: Q4 cumulative year view
A5: Month 12 ARR run-rate | B5: ='Monthly Model'!T13 | C5: Monthly Model
A6: Month 12 net cashflow | B6: ='Monthly Model'!R13 | C6: Monthly Model
A7: Break-even note | B7: Base-case break-even likely around Q4 / Q1 next year, not in first 3 months.

Sheet Inputs
A1: Input | B1: Value | C1: Unit | D1: Meaning | E1: Can edit?
A2: FX USD to EUR | B2: 0.92 | C2: EUR per USD | D2: Перевод долларовой подписки в модельную валюту EUR | E2: yes
A3: Base subscription price | B3: 12.99 | C3: USD / month | D3: Базовая blended цена подписки | E3: yes
A4: App/payment fee | B4: 0.15 | C4: % revenue | D4: Комиссия store/payment/revenue platform | E4: yes
A5: Token revenue per payer | B5: 1.5 | C5: USD / payer / month | D5: Средний upside от premium tokens/video | E5: yes
A6: Paid COGS per payer | B6: 3.2 | C6: EUR / payer / month | D6: AI/image/video COGS для платящего пользователя | E6: yes
A7: Free COGS per free MAU | B7: 0.18 | C7: EUR / free MAU / month | D7: AI/image COGS free users с capped usage | E7: yes
A8: Support cost per payer | B8: 0.6 | C8: EUR / payer / month | D8: Support/admin переменная часть | E8: yes
A9: Opening cash | B9: 0 | C9: EUR | D9: Деньги на старте модели | E9: yes
A10: Year 1 target runway | B10: 120000 | C10: EUR | D10: Ориентир бюджета первого года | E10: yes
A11: Break-even target month | B11: 12 | C11: month | D11: Ожидаемый месяц проверки break-even | E11: yes

Sheet Terms
A1: Term | B1: Simple explanation | C1: Why it matters for AURA
A2: MAU | B2: Активные пользователи за месяц | C2: Показывает реальный размер продукта, не просто скачивания
A3: Paid conversion | B3: Какая доля MAU платит | C3: Главный рычаг выручки
A4: Payers | B4: Количество платящих пользователей | C4: Основа подписочной выручки
A5: COGS | B5: Переменные расходы на AI, картинки, видео, storage, ошибки генерации | C5: Если COGS высокий, видео съедает маржу
A6: CAC | B6: Стоимость привлечения клиента | C6: Нельзя масштабировать, если CAC выше будущей прибыли
A7: Burn | B7: Сколько денег сгорает в месяц | C7: Показывает, сколько runway нужно
A8: Runway / cash need | B8: Сколько денег нужно, чтобы дожить до следующей проверки | C8: Помогает планировать раунды/бюджет
A9: ARR run-rate | B9: Месячная выручка × 12 | C9: Удобный ориентир масштаба бизнеса
A10: Break-even | B10: Месяц, когда выручка покрывает расходы | C10: Показывает шанс стать cashflow-бизнесом
A11: Cash-out | B11: Сценарий продажи/выхода или превращения в денежный бизнес | C11: Возможен только после доказанных retention, CAC, COGS

Sheet Monthly Model
A1: Month | B1: Phase | C1: MAU | D1: Paid conversion | E1: Payers | F1: Gross sub revenue | G1: Payment fee | H1: Net sub revenue | I1: Token revenue | J1: Total revenue | K1: Paid COGS | L1: Free COGS | M1: Support variable | N1: Product/dev/team | O1: Infra/tools | P1: Marketing | Q1: Total spend | R1: Net cashflow | S1: Cumulative cash need | T1: ARR run-rate
A2: 1 | B2: Validation | C2: 100 | D2: 0 | E2: =C2*D2 | F2: =E2*Inputs!$B$3*Inputs!$B$2 | G2: =F2*Inputs!$B$4 | H2: =F2-G2 | I2: =E2*Inputs!$B$5*Inputs!$B$2 | J2: =H2+I2 | K2: =E2*Inputs!$B$6 | L2: =(C2-E2)*Inputs!$B$7 | M2: =E2*Inputs!$B$8 | N2: 6000 | O2: 500 | P2: 2000 | Q2: =K2+L2+M2+N2+O2+P2 | R2: =J2-Q2 | S2: =MAX(0,-SUM($R$2:R2)-Inputs!$B$9) | T2: =J2*12
A3: 2 | B3: Validation | C3: 500 | D3: 0.02 | E3: =C3*D3 | F3: =E3*Inputs!$B$3*Inputs!$B$2 | G3: =F3*Inputs!$B$4 | H3: =F3-G3 | I3: =E3*Inputs!$B$5*Inputs!$B$2 | J3: =H3+I3 | K3: =E3*Inputs!$B$6 | L3: =(C3-E3)*Inputs!$B$7 | M3: =E3*Inputs!$B$8 | N3: 7000 | O3: 700 | P3: 3000 | Q3: =K3+L3+M3+N3+O3+P3 | R3: =J3-Q3 | S3: =MAX(0,-SUM($R$2:R3)-Inputs!$B$9) | T3: =J3*12
A4: 3 | B4: MVP build | C4: 1000 | D4: 0.03 | E4: =C4*D4 | F4: =E4*Inputs!$B$3*Inputs!$B$2 | G4: =F4*Inputs!$B$4 | H4: =F4-G4 | I4: =E4*Inputs!$B$5*Inputs!$B$2 | J4: =H4+I4 | K4: =E4*Inputs!$B$6 | L4: =(C4-E4)*Inputs!$B$7 | M4: =E4*Inputs!$B$8 | N4: 12000 | O4: 1000 | P4: 4000 | Q4: =K4+L4+M4+N4+O4+P4 | R4: =J4-Q4 | S4: =MAX(0,-SUM($R$2:R4)-Inputs!$B$9) | T4: =J4*12
A5: 4 | B5: MVP build | C5: 3000 | D5: 0.027 | E5: =C5*D5 | F5: =E5*Inputs!$B$3*Inputs!$B$2 | G5: =F5*Inputs!$B$4 | H5: =F5-G5 | I5: =E5*Inputs!$B$5*Inputs!$B$2 | J5: =H5+I5 | K5: =E5*Inputs!$B$6 | L5: =(C5-E5)*Inputs!$B$7 | M5: =E5*Inputs!$B$8 | N5: 16000 | O5: 1500 | P5: 6000 | Q5: =K5+L5+M5+N5+O5+P5 | R5: =J5-Q5 | S5: =MAX(0,-SUM($R$2:R5)-Inputs!$B$9) | T5: =J5*12
A6: 5 | B6: Private beta | C6: 6000 | D6: 0.025 | E6: =C6*D6 | F6: =E6*Inputs!$B$3*Inputs!$B$2 | G6: =F6*Inputs!$B$4 | H6: =F6-G6 | I6: =E6*Inputs!$B$5*Inputs!$B$2 | J6: =H6+I6 | K6: =E6*Inputs!$B$6 | L6: =(C6-E6)*Inputs!$B$7 | M6: =E6*Inputs!$B$8 | N6: 20000 | O6: 2200 | P6: 9000 | Q6: =K6+L6+M6+N6+O6+P6 | R6: =J6-Q6 | S6: =MAX(0,-SUM($R$2:R6)-Inputs!$B$9) | T6: =J6*12
A7: 6 | B7: Private beta | C7: 10000 | D7: 0.03 | E7: =C7*D7 | F7: =E7*Inputs!$B$3*Inputs!$B$2 | G7: =F7*Inputs!$B$4 | H7: =F7-G7 | I7: =E7*Inputs!$B$5*Inputs!$B$2 | J7: =H7+I7 | K7: =E7*Inputs!$B$6 | L7: =(C7-E7)*Inputs!$B$7 | M7: =E7*Inputs!$B$8 | N7: 24000 | O7: 3000 | P7: 12000 | Q7: =K7+L7+M7+N7+O7+P7 | R7: =J7-Q7 | S7: =MAX(0,-SUM($R$2:R7)-Inputs!$B$9) | T7: =J7*12
A8: 7 | B8: Public beta | C8: 15000 | D8: 0.03 | E8: =C8*D8 | F8: =E8*Inputs!$B$3*Inputs!$B$2 | G8: =F8*Inputs!$B$4 | H8: =F8-G8 | I8: =E8*Inputs!$B$5*Inputs!$B$2 | J8: =H8+I8 | K8: =E8*Inputs!$B$6 | L8: =(C8-E8)*Inputs!$B$7 | M8: =E8*Inputs!$B$8 | N8: 26000 | O8: 3500 | P8: 16000 | Q8: =K8+L8+M8+N8+O8+P8 | R8: =J8-Q8 | S8: =MAX(0,-SUM($R$2:R8)-Inputs!$B$9) | T8: =J8*12
A9: 8 | B9: Public beta | C9: 25000 | D9: 0.03 | E9: =C9*D9 | F9: =E9*Inputs!$B$3*Inputs!$B$2 | G9: =F9*Inputs!$B$4 | H9: =F9-G9 | I9: =E9*Inputs!$B$5*Inputs!$B$2 | J9: =H9+I9 | K9: =E9*Inputs!$B$6 | L9: =(C9-E9)*Inputs!$B$7 | M9: =E9*Inputs!$B$8 | N9: 30000 | O9: 4500 | P9: 22000 | Q9: =K9+L9+M9+N9+O9+P9 | R9: =J9-Q9 | S9: =MAX(0,-SUM($R$2:R9)-Inputs!$B$9) | T9: =J9*12
A10: 9 | B10: Public beta | C10: 40000 | D10: 0.03 | E10: =C10*D10 | F10: =E10*Inputs!$B$3*Inputs!$B$2 | G10: =F10*Inputs!$B$4 | H10: =F10-G10 | I10: =E10*Inputs!$B$5*Inputs!$B$2 | J10: =H10+I10 | K10: =E10*Inputs!$B$6 | L10: =(C10-E10)*Inputs!$B$7 | M10: =E10*Inputs!$B$8 | N10: 33000 | O10: 5500 | P10: 30000 | Q10: =K10+L10+M10+N10+O10+P10 | R10: =J10-Q10 | S10: =MAX(0,-SUM($R$2:R10)-Inputs!$B$9) | T10: =J10*12
A11: 10 | B11: Launch | C11: 60000 | D11: 0.03 | E11: =C11*D11 | F11: =E11*Inputs!$B$3*Inputs!$B$2 | G11: =F11*Inputs!$B$4 | H11: =F11-G11 | I11: =E11*Inputs!$B$5*Inputs!$B$2 | J11: =H11+I11 | K11: =E11*Inputs!$B$6 | L11: =(C11-E11)*Inputs!$B$7 | M11: =E11*Inputs!$B$8 | N11: 38000 | O11: 7000 | P11: 40000 | Q11: =K11+L11+M11+N11+O11+P11 | R11: =J11-Q11 | S11: =MAX(0,-SUM($R$2:R11)-Inputs!$B$9) | T11: =J11*12
A12: 11 | B12: Launch | C12: 90000 | D12: 0.033 | E12: =C12*D12 | F12: =E12*Inputs!$B$3*Inputs!$B$2 | G12: =F12*Inputs!$B$4 | H12: =F12-G12 | I12: =E12*Inputs!$B$5*Inputs!$B$2 | J12: =H12+I12 | K12: =E12*Inputs!$B$6 | L12: =(C12-E12)*Inputs!$B$7 | M12: =E12*Inputs!$B$8 | N12: 42000 | O12: 8500 | P12: 50000 | Q12: =K12+L12+M12+N12+O12+P12 | R12: =J12-Q12 | S12: =MAX(0,-SUM($R$2:R12)-Inputs!$B$9) | T12: =J12*12
A13: 12 | B13: Launch | C13: 150000 | D13: 0.045 | E13: =C13*D13 | F13: =E13*Inputs!$B$3*Inputs!$B$2 | G13: =F13*Inputs!$B$4 | H13: =F13-G13 | I13: =E13*Inputs!$B$5*Inputs!$B$2 | J13: =H13+I13 | K13: =E13*Inputs!$B$6 | L13: =(C13-E13)*Inputs!$B$7 | M13: =E13*Inputs!$B$8 | N13: 50000 | O13: 11000 | P13: 65000 | Q13: =K13+L13+M13+N13+O13+P13 | R13: =J13-Q13 | S13: =MAX(0,-SUM($R$2:R13)-Inputs!$B$9) | T13: =J13*12
... A37: 36 | B37: Scale | C37: 6200000 | D37: 0.072 | E37: =C37*D37 | F37: =E37*Inputs!$B$3*Inputs!$B$2 | G37: =F37*Inputs!$B$4 | H37: =F37-G37 | I37: =E37*Inputs!$B$5*Inputs!$B$2 | J37: =H37+I37 | K37: =E37*Inputs!$B$6 | L37: =(C37-E37)*Inputs!$B$7 | M37: =E37*Inputs!$B$8 | N37: 470000 | O37: 330000 | P37: 2700000 | Q37: =K37+L37+M37+N37+O37+P37 | R37: =J37-Q37 | S37: =MAX(0,-SUM($R$2:R37)-Inputs!$B$9) | T37: =J37*12

Sheet Quarterly Summary
A1: Quarter | B1: Start month | C1: End month | D1: Revenue | E1: Spend | F1: Net cashflow | G1: Ending cash need | H1: ARR run-rate
A2: Q1 | B2: 1 | C2: 3 | D2: =SUM('Monthly Model'!J2:J4) | E2: =SUM('Monthly Model'!Q2:Q4) | F2: =SUM('Monthly Model'!R2:R4) | G2: ='Monthly Model'!S4 | H2: ='Monthly Model'!T4
A3: Q2 | B3: 4 | C3: 6 | D3: =SUM('Monthly Model'!J5:J7) | E3: =SUM('Monthly Model'!Q5:Q7) | F3: =SUM('Monthly Model'!R5:R7) | G3: ='Monthly Model'!S7 | H3: ='Monthly Model'!T7
A4: Q3 | B4: 7 | C4: 9 | D4: =SUM('Monthly Model'!J8:J10) | E4: =SUM('Monthly Model'!Q8:Q10) | F4: =SUM('Monthly Model'!R8:R10) | G4: ='Monthly Model'!S10 | H4: ='Monthly Model'!T10
A5: Q4 | B5: 10 | C5: 12 | D5: =SUM('Monthly Model'!J11:J13) | E5: =SUM('Monthly Model'!Q11:Q13) | F5: =SUM('Monthly Model'!R11:R13) | G5: ='Monthly Model'!S13 | H5: ='Monthly Model'!T13
A6: Q5 | B6: 13 | C6: 15 | D6: =SUM('Monthly Model'!J14:J16) | E6: =SUM('Monthly Model'!Q14:Q16) | F6: =SUM('Monthly Model'!R14:R16) | G6: ='Monthly Model'!S16 | H6: ='Monthly Model'!T16
A7: Q6 | B7: 16 | C7: 18 | D7: =SUM('Monthly Model'!J17:J19) | E7: =SUM('Monthly Model'!Q17:Q19) | F7: =SUM('Monthly Model'!R17:R19) | G7: ='Monthly Model'!S19 | H7: ='Monthly Model'!T19
A8: Q7 | B8: 19 | C8: 21 | D8: =SUM('Monthly Model'!J20:J22) | E8: =SUM('Monthly Model'!Q20:Q22) | F8: =SUM('Monthly Model'!R20:R22) | G8: ='Monthly Model'!S22 | H8: ='Monthly Model'!T22
A9: Q8 | B9: 22 | C9: 24 | D9: =SUM('Monthly Model'!J23:J25) | E9: =SUM('Monthly Model'!Q23:Q25) | F9: =SUM('Monthly Model'!R23:R25) | G9: ='Monthly Model'!S25 | H9: ='Monthly Model'!T25
A10: Q9 | B10: 25 | C10: 27 | D10: =SUM('Monthly Model'!J26:J28) | E10: =SUM('Monthly Model'!Q26:Q28) | F10: =SUM('Monthly Model'!R26:R28) | G10: ='Monthly Model'!S28 | H10: ='Monthly Model'!T28
A11: Q10 | B11: 28 | C11: 30 | D11: =SUM('Monthly Model'!J29:J31) | E11: =SUM('Monthly Model'!Q29:Q31) | F11: =SUM('Monthly Model'!R29:R31) | G11: ='Monthly Model'!S31 | H11: ='Monthly Model'!T31
A12: Q11 | B12: 31 | C12: 33 | D12: =SUM('Monthly Model'!J32:J34) | E12: =SUM('Monthly Model'!Q32:Q34) | F12: =SUM('Monthly Model'!R32:R34) | G12: ='Monthly Model'!S34 | H12: ='Monthly Model'!T34
A13: Q12 | B13: 34 | C13: 36 | D13: =SUM('Monthly Model'!J35:J37) | E13: =SUM('Monthly Model'!Q35:Q37) | F13: =SUM('Monthly Model'!R35:R37) | G13: ='Monthly Model'!S37 | H13: ='Monthly Model'!T37

Sheet Annual Scenarios
A1: Scenario | B1: Year 1 ARR | C1: Year 2 ARR | D1: Year 3 ARR | E1: Cash need | F1: Interpretation
A2: Conservative | B2: $40k-$120k | C2: $250k-$600k | D2: $0.8M-$1.5M | E2: €80k-€150k | F2: Small cashflow product if CAC stays low and team remains compact
A3: Base | B3: $150k-$400k | C3: $0.8M-$2M | D3: $3M-$6M | E3: €150k-€500k | F3: Standalone business / seed story if retention and annual plans work
A4: Strong | B4: $0.5M-$1M | C4: $3M-$6M | D4: $8M-$15M | E4: €500k+ | F4: Strategic interest from wellness, astrology, AI companion or creator platforms
A5: Stop / pivot | B5: <$40k | C5: <$250k | D5: No retention | E5: Stop after validation | F5: Stop if D1 <20%, paid intent <5%, CAC/LTV broken or Canvas causality is unclear

Sheet Unit Economics
A1: Metric | B1: Formula / value | C1: Base result | D1: Why it matters
A2: Net subscription per payer | B2: =Inputs!B3*Inputs!B2*(1-Inputs!B4) | C2: =Inputs!B3*Inputs!B2*(1-Inputs!B4) | D2: Revenue retained after payment/store fee
A3: Token revenue per payer | B3: =Inputs!B5*Inputs!B2 | C3: =Inputs!B5*Inputs!B2 | D3: Optional premium upside
A4: Variable COGS per payer | B4: =Inputs!B6+Inputs!B8 | C4: =Inputs!B6+Inputs!B8 | D4: AI/video/image/support variable cost
A5: Contribution per payer | B5: =B2+B3-B4 | C5: =C2+C3-C4 | D5: What is left before marketing and fixed team costs
A6: Free MAU COGS | B6: =Inputs!B7 | C6: =Inputs!B7 | D6: Free usage must stay capped
A7: Break-even payers at €25k fixed/month | B7: =25000/C5 | C7: =25000/C5 | D7: Rough minimum payer base to cover compact ops

Sheet Checks
A1: Check | B1: Formula | C1: Expected | D1: Status
A2: Revenue non-negative | B2: =MIN('Monthly Model'!J2:J37)>=0 | C2: TRUE | D2: =IF(B2=C2,"OK","CHECK")
A3: Spend non-negative | B3: =MIN('Monthly Model'!Q2:Q37)>=0 | C3: TRUE | D3: =IF(B3=C3,"OK","CHECK")
A4: Cash need visible | B4: =MAX('Monthly Model'!S2:S37)>0 | C4: TRUE | D4: =IF(B4=C4,"OK","CHECK")
A5: Month count | B5: =COUNT('Monthly Model'!A2:A37) | C5: 36 | D5: =IF(B5=C5,"OK","CHECK")
